pytest_edit.py
pytest_edit-1.2.dist-info/LICENSE.md
pytest_edit-1.2.dist-info/METADATA
pytest_edit-1.2.dist-info/WHEEL
pytest_edit-1.2.dist-info/entry_points.txt
pytest_edit-1.2.dist-info/top_level.txt
pytest_edit-1.2.dist-info/RECORD
