Metadata-Version: 2.1
Name: pytest-edit
Version: 1.2
Summary: Edit the source code of a failed test with `pytest --edit`.
Author-email: Błażej Michalik <code.mrmino@gmail.com>
License: MIT
Project-URL: Homepage, https://github.com/mrmino/pytest-edit
Classifier: Intended Audience :: Developers
Classifier: License :: OSI Approved :: MIT License
Classifier: Programming Language :: Python :: 3
Classifier: Framework :: Pytest
License-File: LICENSE.md
Requires-Dist: pytest
